binario_para_decimal/bcd_to_7segment.v
module BCD_to_7Segment(
    input wire [3:0] bcd_code,
    output reg [6:0] seg
);

always @(*) begin
    case (bcd_code)
        'd0 : seg = 7'b0000001;
        'd1 : seg = 7'b1001111;
        'd2 : seg = 7'b0010010;
        'd3 : seg = 7'b0000110;
        'd4 : seg = 7'b1001100;
        'd5 : seg = 7'b0100100;
        'd6 : seg = 7'b0100000;
        'd7 : seg = 7'b0001111;
        'd8 : seg = 7'b0000000;
        'd9 : seg = 7'b0000100;
        default : seg = 7'b1111111; 
    endcase
end
    
endmodule

binario_para_decimal/conversor.v
module Converter (
    input wire clk,
    input wire reset,
    input wire start,
    input wire [15:0] number,
    output wire [19:0] bcd_number
);

localparam IDLE = 2'b00;
localparam RUN  = 2'b01;
localparam SUM  = 2'b10;

reg [1:0] state;
reg [3:0] bcd_number_1, bcd_number_2, bcd_number_3, bcd_number_4, bcd_number_5;
reg [19:0] input_number;

wire zero = ~( |input_number );

initial begin
    bcd_number_1 = 4'h0;
    bcd_number_2 = 4'h0;
    bcd_number_3 = 4'h0;
    bcd_number_4 = 4'h0;
    bcd_number_5 = 4'h0;
    state = IDLE;
end

always @(posedge clk ) begin
    if(reset == 1'b1) begin
        bcd_number_1 <= 4'h0;
        bcd_number_2 <= 4'h0;
        bcd_number_3 <= 4'h0;
        bcd_number_4 <= 4'h0;
        bcd_number_5 <= 4'h0;
        state <= IDLE;
        input_number <= 20'h00000;
    end else begin
        case (state)
            IDLE: begin
                if(start == 1'b1) begin
                    state <= RUN;
                    bcd_number_1 <= 4'h0;
                    bcd_number_2 <= 4'h0;
                    bcd_number_3 <= 4'h0;
                    bcd_number_4 <= 4'h0;
                    bcd_number_5 <= 4'h0;
                    input_number <= number;
                end
                else state <= IDLE;
            end
            RUN: begin
                if(zero == 1'b0) begin
                    bcd_number_1 <= {bcd_number_1[2:0], input_number[19]};
                    bcd_number_2 <= {bcd_number_2[2:0], bcd_number_1[3]};
                    bcd_number_3 <= {bcd_number_3[2:0], bcd_number_2[3]};
                    bcd_number_4 <= {bcd_number_4[2:0], bcd_number_3[3]};
                    bcd_number_5 <= {bcd_number_5[2:0], bcd_number_4[3]};
                    input_number <= {input_number[18:0], 1'b0};

                    state <= SUM;
                end else begin
                    state <= IDLE;
                end
            end
            SUM: begin
                if(zero == 1'b0) begin
                    if(bcd_number_1 > 'd4)
                        bcd_number_1 <= bcd_number_1 + 'd3;
                    if(bcd_number_2 > 'd4)
                        bcd_number_2 <= bcd_number_2 + 'd3;
                    if(bcd_number_3 > 'd4)
                        bcd_number_3 <= bcd_number_3 + 'd3;
                    if(bcd_number_4 > 'd4)
                        bcd_number_4 <= bcd_number_4 + 'd3;
                    if(bcd_number_5 > 'd4)
                        bcd_number_5 <= bcd_number_5 + 'd3;
                        
                    state <= RUN;
                end else begin
                    state <= IDLE;
                end
            end
            default: state <= IDLE;
        endcase
    end
end

assign bcd_number = {bcd_number_5, bcd_number_4, bcd_number_3, bcd_number_2, bcd_number_1};
    
endmodule

binario_para_decimal/main.v
module top (
    input wire clk,
    input wire reset,
    output wire [6:0] bcd_1,
    output wire [6:0] bcd_2,
    output wire [6:0] bcd_3,
    output wire [6:0] bcd_4,
    output wire [6:0] bcd_5
);

wire [19:0] bcd_number;
reg [15:0] number;
reg start, counter;

initial begin
    number = 16'd2555;
    counter = 1'b0;
    start = 1'b0;
end

always @(clk) begin
    if(reset == 1'b1) begin
        counter <= 1'b0;
        start <= 1'b0;
    end else begin
        if(counter == 1'b1 && start == 1'b1) begin
            start <= 1'b0;
        end else if(counter == 1'b0 && start == 1'b0) begin
            start <= 1'b1;
            counter <= 1'b1;
        end 
    end
end

Converter Converter (
    .clk(clk),
    .reset(reset),
    .start(start),
    .number(number),
    .bcd_number(bcd_number)
);

BCD_to_7Segment bcd_m_1(
    .bcd_code(bcd_number[3:0]),
    .seg(bcd_1)
);

BCD_to_7Segment bcd_m_2(
    .bcd_code(bcd_number[7:4]),
    .seg(bcd_2)
);

BCD_to_7Segment bcd_m_3(
    .bcd_code(bcd_number[11:8]),
    .seg(bcd_3)
);

BCD_to_7Segment bcd_m_4(
    .bcd_code(bcd_number[15:12]),
    .seg(bcd_4)
);

BCD_to_7Segment bcd_m_5(
    .bcd_code(bcd_number[19:16]),
    .seg(bcd_5)
);
    
endmodule

binario_para_decimal/test.v
module testbench ();
    
reg clk, reset;

always #1 clk = ~clk;

top top(
    .clk(clk),
    .reset(reset)
);

initial begin
    $dumpfile("test.vcd");
    $dumpvars;

    clk = 1'b0;
    reset = 1'b1;

    #4

    reset = 1'b0;

    #200

    $finish;
end

endmodule

binario_para_decimal/test.vcd
$date
	Mon Apr  1 18:17:12 2024
$end
$version
	Icarus Verilog
$end
$timescale
	1s
$end
$scope module testbench $end
$var reg 1 ! clk $end
$var reg 1 " reset $end
$scope module top $end
$var wire 1 ! clk $end
$var wire 1 " reset $end
$var wire 20 # bcd_number [19:0] $end
$var wire 7 $ bcd_5 [6:0] $end
$var wire 7 % bcd_4 [6:0] $end
$var wire 7 & bcd_3 [6:0] $end
$var wire 7 ' bcd_2 [6:0] $end
$var wire 7 ( bcd_1 [6:0] $end
$var reg 1 ) counter $end
$var reg 16 * number [15:0] $end
$var reg 1 + start $end
$scope module Converter $end
$var wire 1 ! clk $end
$var wire 16 , number [15:0] $end
$var wire 1 " reset $end
$var wire 1 + start $end
$var wire 1 - zero $end
$var wire 20 . bcd_number [19:0] $end
$var parameter 2 / IDLE $end
$var parameter 2 0 RUN $end
$var parameter 2 1 SUM $end
$var reg 4 2 bcd_number_1 [3:0] $end
$var reg 4 3 bcd_number_2 [3:0] $end
$var reg 4 4 bcd_number_3 [3:0] $end
$var reg 4 5 bcd_number_4 [3:0] $end
$var reg 4 6 bcd_number_5 [3:0] $end
$var reg 20 7 input_number [19:0] $end
$var reg 2 8 state [1:0] $end
$upscope $end
$scope module bcd_m_1 $end
$var wire 4 9 bcd_code [3:0] $end
$var reg 7 : seg [6:0] $end
$upscope $end
$scope module bcd_m_2 $end
$var wire 4 ; bcd_code [3:0] $end
$var reg 7 < seg [6:0] $end
$upscope $end
$scope module bcd_m_3 $end
$var wire 4 = bcd_code [3:0] $end
$var reg 7 > seg [6:0] $end
$upscope $end
$scope module bcd_m_4 $end
$var wire 4 ? bcd_code [3:0] $end
$var reg 7 @ seg [6:0] $end
$upscope $end
$scope module bcd_m_5 $end
$var wire 4 A bcd_code [3:0] $end
$var reg 7 B seg [6:0] $end
$upscope $end
$upscope $end
$upscope $end
$enddefinitions $end
$comment Show the parameter values. $end
$dumpall
b10 1
b1 0
b0 /
$end
#0
$dumpvars
b1 B
b0 A
b1 @
b0 ?
b1 >
b0 =
b1 <
b0 ;
b1 :
b0 9
b0 8
bx 7
b0 6
b0 5
b0 4
b0 3
b0 2
b0 .
x-
b100111111011 ,
0+
b100111111011 *
0)
b1 (
b1 '
b1 &
b1 %
b1 $
b0 #
1"
0!
$end
#1
1-
b0 7
1!
#2
0!
#3
1!
#4
1)
1+
0!
0"
#5
0-
b100111111011 7
b1 8
0+
1!
#6
0!
#7
b10 8
b1001111110110 7
1!
#8
0!
#9
b1 8
1!
#10
0!
#11
b10 8
b10011111101100 7
1!
#12
0!
#13
b1 8
1!
#14
0!
#15
b10 8
b100111111011000 7
1!
#16
0!
#17
b1 8
1!
#18
0!
#19
b10 8
b1001111110110000 7
1!
#20
0!
#21
b1 8
1!
#22
0!
#23
b10 8
b10011111101100000 7
1!
#24
0!
#25
b1 8
1!
#26
0!
#27
b10 8
b100111111011000000 7
1!
#28
0!
#29
b1 8
1!
#30
0!
#31
b10 8
b1001111110110000000 7
1!
#32
0!
#33
b1 8
1!
#34
0!
#35
b10 8
b10011111101100000000 7
1!
#36
0!
#37
b1 8
1!
#38
0!
#39
b1001111 (
b1001111 :
b1 9
b10 8
b111111011000000000 7
b1 #
b1 .
b1 2
1!
#40
0!
#41
b1 8
1!
#42
0!
#43
b10010 (
b10010 :
b10 9
b10 8
b1111110110000000000 7
b10 #
b10 .
b10 2
1!
#44
0!
#45
b1 8
1!
#46
0!
#47
b1001100 (
b1001100 :
b100 9
b10 8
b11111101100000000000 7
b100 #
b100 .
b100 2
1!
#48
0!
#49
b1 8
1!
#50
0!
#51
b100 (
b100 :
b1001 9
b10 8
b11111011000000000000 7
b1001 #
b1001 .
b1001 2
1!
#52
0!
#53
b1111111 (
b1111111 :
b1100 9
b1 8
b1100 #
b1100 .
b1100 2
1!
#54
0!
#55
b1001111 '
b1001111 <
b100 (
b100 :
b1 ;
b1001 9
b10 8
b11110110000000000000 7
b1 3
b11001 #
b11001 .
b1001 2
1!
#56
0!
#57
b1111111 (
b1111111 :
b1100 9
b1 8
b11100 #
b11100 .
b1100 2
1!
#58
0!
#59
b110 '
b110 <
b100 (
b100 :
b11 ;
b1001 9
b10 8
b11101100000000000000 7
b11 3
b111001 #
b111001 .
b1001 2
1!
#60
0!
#61
b1111111 (
b1111111 :
b1100 9
b1 8
b111100 #
b111100 .
b1100 2
1!
#62
0!
#63
b1111 '
b1111 <
b100 (
b100 :
b111 ;
b1001 9
b10 8
b11011000000000000000 7
b111 3
b1111001 #
b1111001 .
b1001 2
1!
#64
0!
#65
b1111111 '
b1111111 <
b1111111 (
b1111111 :
b1010 ;
b1100 9
b1 8
b1010 3
b10101100 #
b10101100 .
b1100 2
1!
#66
0!
#67
b1001111 &
b1001111 >
b100100 '
b100100 <
b100 (
b100 :
b1 =
b101 ;
b1001 9
b10 8
b10110000000000000000 7
b1 4
b101 3
b101011001 #
b101011001 .
b1001 2
1!
#68
0!
#69
b0 '
b0 <
b1111111 (
b1111111 :
b1000 ;
b1100 9
b1 8
b1000 3
b110001100 #
b110001100 .
b1100 2
1!
#70
0!
#71
b110 &
b110 >
b1001111 '
b1001111 <
b100 (
b100 :
b11 =
b1 ;
b1001 9
b10 8
b1100000000000000000 7
b11 4
b1 3
b1100011001 #
b1100011001 .
b1001 2
1!
#72
0!
#73
b1111111 (
b1111111 :
b1100 9
b1 8
b1100011100 #
b1100011100 .
b1100 2
1!
#74
0!
#75
b100000 &
b100000 >
b110 '
b110 <
b0 (
b0 :
b110 =
b11 ;
b1000 9
b10 8
b11000000000000000000 7
b110 4
b11 3
b11000111000 #
b11000111000 .
b1000 2
1!
#76
0!
#77
b100 &
b100 >
b1111111 (
b1111111 :
b1001 =
b1011 9
b1 8
b1001 4
b100100111011 #
b100100111011 .
b1011 2
1!
#78
0!
#79
b1001111 %
b1001111 @
b10010 &
b10010 >
b1111 '
b1111 <
b1111 (
b1111 :
b1 ?
b10 =
b111 ;
b111 9
b10 8
b10000000000000000000 7
b1 5
b10 4
b111 3
b1001001110111 #
b1001001110111 .
b111 2
1!
#80
0!
#81
b1111111 '
b1111111 <
b1111111 (
b1111111 :
b1010 ;
b1010 9
b1 8
b1010 3
b1001010101010 #
b1001010101010 .
b1010 2
1!
#82
0!
#83
b10010 %
b10010 @
b100100 &
b100100 >
b100100 '
b100100 <
b100100 (
b100100 :
1-
b10 ?
b101 =
b101 ;
b101 9
b10 8
b0 7
b10 5
b101 4
b101 3
b10010101010101 #
b10010101010101 .
b101 2
1!
#84
0!
#85
b0 8
1!
